CHANGES.txt
COPYRIGHT.txt
CREDITS.txt
LICENSE.txt
MANIFEST.in
README.txt
bootstrap.py
buildout.cfg
setup.py
src/hurry/__init__.py
src/hurry.jquerytools.egg-info/PKG-INFO
src/hurry.jquerytools.egg-info/SOURCES.txt
src/hurry.jquerytools.egg-info/dependency_links.txt
src/hurry.jquerytools.egg-info/entry_points.txt
src/hurry.jquerytools.egg-info/namespace_packages.txt
src/hurry.jquerytools.egg-info/not-zip-safe
src/hurry.jquerytools.egg-info/requires.txt
src/hurry.jquerytools.egg-info/top_level.txt
src/hurry/jquerytools/__init__.py
src/hurry/jquerytools/jquerytools.txt
src/hurry/jquerytools/prepare.py
src/hurry/jquerytools/tests.py
src/hurry/jquerytools/jquerytools-build/jquery.tools.min.js