Metadata-Version: 1.0
Name: hurry.jquerytools
Version: 1.2.5.1
Summary: hurry.resource style resources for jquerytools.
Home-page: http://pypi.python.org/hurry.jquerytools
Author: Christian Klinger
Author-email: cklinger@novareto.de
License: ZPL 2.1
Keywords: jQuery jquerytools Zope3 Popup
Platform: UNKNOWN
